[
    {
        "acousticness": 0.08,
        "album": "Un Verano Sin Ti",
        "artist": "Bad Bunny",
        "danceability": 0.647,
        "energy": 0.686,
        "field1": 0,
        "length(ms)": 258298,
        "liveness": 0.528,
        "popularity": 93,
        "release_date": "2022-05-06",
        "songname": "Ojitos Lindos",
        "tempo": 79.928,
        "valence": 0.268
    },
    {
        "acousticness": 0.356,
        "album": "Un Verano Sin Ti",
        "artist": "Bad Bunny",
        "danceability": 0.564,
        "energy": 0.903,
        "field1": 1,
        "length(ms)": 230400,
        "liveness": 0.175,
        "popularity": 87,
        "release_date": "2022-05-06",
        "songname": "Después de la Playa",
        "tempo": 78.293,
        "valence": 0.607
    },
    {
        "acousticness": 0.276,
        "album": "Yonaguni",
        "artist": "Bad Bunny",
        "danceability": 0.644,
        "energy": 0.648,
        "field1": 2,
        "length(ms)": 206710,
        "liveness": 0.135,
        "popularity": 86,
        "release_date": "2021-06-04",
        "songname": "Yonaguni",
        "tempo": 179.951,
        "valence": 0.44
    },
    {
        "acousticness": 0.401,
        "album": "DÁKITI",
        "artist": "Bad Bunny",
        "danceability": 0.731,
        "energy": 0.573,
        "field1": 3,
        "length(ms)": 205090,
        "liveness": 0.113,
        "popularity": 82,
        "release_date": "2020-10-30",
        "songname": "DÁKITI",
        "tempo": 109.928,
        "valence": 0.145
    },
    {
        "acousticness": 0.0151,
        "album": "Un Verano Sin Ti",
        "artist": "Bad Bunny",
        "danceability": 0.829,
        "energy": 0.799,
        "field1": 4,
        "length(ms)": 227628,
        "liveness": 0.242,
        "popularity": 89,
        "release_date": "2022-05-06",
        "songname": "Party",
        "tempo": 97.013,
        "valence": 0.471
    },
    {
        "acousticness": 0.0901,
        "album": "Un Verano Sin Ti",
        "artist": "Bad Bunny",
        "danceability": 0.911,
        "energy": 0.712,
        "field1": 5,
        "length(ms)": 178567,
        "liveness": 0.0933,
        "popularity": 96,
        "release_date": "2022-05-06",
        "songname": "Me Porto Bonito",
        "tempo": 92.005,
        "valence": 0.425
    },
    {
        "acousticness": 0.294,
        "album": "Un Verano Sin Ti",
        "artist": "Bad Bunny",
        "danceability": 0.804,
        "energy": 0.674,
        "field1": 6,
        "length(ms)": 245939,
        "liveness": 0.115,
        "popularity": 92,
        "release_date": "2022-05-06",
        "songname": "Moscow Mule",
        "tempo": 99.968,
        "valence": 0.292
    },
    {
        "acousticness": 0.0363,
        "album": "Vete",
        "artist": "Bad Bunny",
        "danceability": 0.886,
        "energy": 0.672,
        "field1": 7,
        "length(ms)": 192024,
        "liveness": 0.101,
        "popularity": 78,
        "release_date": "2019-11-21",
        "songname": "Vete",
        "tempo": 91.976,
        "valence": 0.526
    },
    {
        "acousticness": 0.0326,
        "album": "YHLQMDLG",
        "artist": "Bad Bunny",
        "danceability": 0.744,
        "energy": 0.868,
        "field1": 8,
        "length(ms)": 206420,
        "liveness": 0.0822,
        "popularity": 83,
        "release_date": "2020-02-29",
        "songname": "La Santa",
        "tempo": 93.037,
        "valence": 0.586
    },
    {
        "acousticness": 0.229,
        "album": "Un Verano Sin Ti",
        "artist": "Bad Bunny",
        "danceability": 0.663,
        "energy": 0.786,
        "field1": 9,
        "length(ms)": 198367,
        "liveness": 0.219,
        "popularity": 88,
        "release_date": "2022-05-06",
        "songname": "La Corriente",
        "tempo": 196.12,
        "valence": 0.579
    },
    {
        "acousticness": 0.152,
        "album": "OASIS",
        "artist": "J Balvin",
        "danceability": 0.754,
        "energy": 0.646,
        "field1": 10,
        "length(ms)": 242573,
        "liveness": 0.108,
        "popularity": 88,
        "release_date": "2019-06-28",
        "songname": "LA CANCIÓN",
        "tempo": 176.089,
        "valence": 0.429
    },
    {
        "acousticness": 0.402,
        "album": "YHLQMDLG",
        "artist": "Bad Bunny",
        "danceability": 0.9,
        "energy": 0.603,
        "field1": 11,
        "length(ms)": 170971,
        "liveness": 0.134,
        "popularity": 81,
        "release_date": "2020-02-29",
        "songname": "Si Veo a Tu Mamá",
        "tempo": 129.928,
        "valence": 0.824
    },
    {
        "acousticness": 0.6,
        "album": "Callaita",
        "artist": "Bad Bunny",
        "danceability": 0.61,
        "energy": 0.624,
        "field1": 12,
        "length(ms)": 250533,
        "liveness": 0.243,
        "popularity": 79,
        "release_date": "2019-05-31",
        "songname": "Callaita",
        "tempo": 176.169,
        "valence": 0.244
    },
    {
        "acousticness": 0.0225,
        "album": "Un Verano Sin Ti",
        "artist": "Bad Bunny",
        "danceability": 0.795,
        "energy": 0.684,
        "field1": 13,
        "length(ms)": 237894,
        "liveness": 0.658,
        "popularity": 89,
        "release_date": "2022-05-06",
        "songname": "Tarot",
        "tempo": 114.011,
        "valence": 0.419
    },
    {
        "acousticness": 0.144,
        "album": "No Me Conoce (Remix)",
        "artist": "Jhay Cortez",
        "danceability": 0.794,
        "energy": 0.79,
        "field1": 14,
        "length(ms)": 307546,
        "liveness": 0.0893,
        "popularity": 75,
        "release_date": "2019-05-17",
        "songname": "No Me Conoce - Remix",
        "tempo": 91.984,
        "valence": 0.577
    },
    {
        "acousticness": 0.0626,
        "album": "X 100PRE",
        "artist": "Bad Bunny",
        "danceability": 0.672,
        "energy": 0.594,
        "field1": 15,
        "length(ms)": 169247,
        "liveness": 0.152,
        "popularity": 82,
        "release_date": "2018-12-23",
        "songname": "Si Estuviésemos Juntos",
        "tempo": 171.854,
        "valence": 0.158
    },
    {
        "acousticness": 0.0706,
        "album": "Un Verano Sin Ti",
        "artist": "Bad Bunny",
        "danceability": 0.876,
        "energy": 0.498,
        "field1": 16,
        "length(ms)": 173119,
        "liveness": 0.143,
        "popularity": 92,
        "release_date": "2022-05-06",
        "songname": "Neverita",
        "tempo": 122.016,
        "valence": 0.428
    },
    {
        "acousticness": 0.169,
        "album": "YHLQMDLG",
        "artist": "Bad Bunny",
        "danceability": 0.86,
        "energy": 0.791,
        "field1": 17,
        "length(ms)": 175918,
        "liveness": 0.106,
        "popularity": 82,
        "release_date": "2020-02-29",
        "songname": "A Tu Merced",
        "tempo": 92.023,
        "valence": 0.887
    },
    {
        "acousticness": 0.234,
        "album": "EL ÚLTIMO TOUR DEL MUNDO",
        "artist": "Bad Bunny",
        "danceability": 0.811,
        "energy": 0.637,
        "field1": 18,
        "length(ms)": 130013,
        "liveness": 0.118,
        "popularity": 80,
        "release_date": "2020-11-27",
        "songname": "TE MUDASTE",
        "tempo": 92.025,
        "valence": 0.471
    },
    {
        "acousticness": 0.141,
        "album": "Un Verano Sin Ti",
        "artist": "Bad Bunny",
        "danceability": 0.801,
        "energy": 0.475,
        "field1": 19,
        "length(ms)": 213061,
        "liveness": 0.0639,
        "popularity": 94,
        "release_date": "2022-05-06",
        "songname": "Efecto",
        "tempo": 98.047,
        "valence": 0.234
    },
    {
        "acousticness": 0.0889,
        "album": "Lo Siento BB:/ (with Bad Bunny & Julieta Venegas)",
        "artist": "Tainy",
        "danceability": 0.639,
        "energy": 0.703,
        "field1": 20,
        "length(ms)": 207301,
        "liveness": 0.0865,
        "popularity": 86,
        "release_date": "2021-10-05",
        "songname": "Lo Siento BB:/ (with Bad Bunny & Julieta Venegas)",
        "tempo": 169.888,
        "valence": 0.138
    },
    {
        "acousticness": 0.0861,
        "album": "YHLQMDLG",
        "artist": "Bad Bunny",
        "danceability": 0.685,
        "energy": 0.848,
        "field1": 21,
        "length(ms)": 163084,
        "liveness": 0.0783,
        "popularity": 79,
        "release_date": "2020-02-29",
        "songname": "La Difícil",
        "tempo": 179.87,
        "valence": 0.761
    },
    {
        "acousticness": 0.0141,
        "album": "MIA (feat. Drake)",
        "artist": "Bad Bunny",
        "danceability": 0.817,
        "energy": 0.539,
        "field1": 22,
        "length(ms)": 210367,
        "liveness": 0.099,
        "popularity": 78,
        "release_date": "2018-10-11",
        "songname": "MIA (feat. Drake)",
        "tempo": 97.062,
        "valence": 0.158
    },
    {
        "acousticness": 0.542,
        "album": "Te Boté (Remix)",
        "artist": "Nio Garcia",
        "danceability": 0.903,
        "energy": 0.675,
        "field1": 23,
        "length(ms)": 417920,
        "liveness": 0.0595,
        "popularity": 77,
        "release_date": "2018-04-13",
        "songname": "Te Boté - Remix",
        "tempo": 96.507,
        "valence": 0.442
    },
    {
        "acousticness": 0.0564,
        "album": "Solita",
        "artist": "Ozuna",
        "danceability": 0.807,
        "energy": 0.633,
        "field1": 24,
        "length(ms)": 311726,
        "liveness": 0.107,
        "popularity": 77,
        "release_date": "2018-01-19",
        "songname": "Solita",
        "tempo": 138.038,
        "valence": 0.325
    },
    {
        "acousticness": 0.0946,
        "album": "CÓMO SE SIENTE (Remix)",
        "artist": "Jhayco",
        "danceability": 0.807,
        "energy": 0.606,
        "field1": 25,
        "length(ms)": 227520,
        "liveness": 0.119,
        "popularity": 81,
        "release_date": "2020-05-09",
        "songname": "CÓMO SE SIENTE - Remix",
        "tempo": 92.988,
        "valence": 0.304
    },
    {
        "acousticness": 0.31,
        "album": "YHLQMDLG",
        "artist": "Bad Bunny",
        "danceability": 0.737,
        "energy": 0.766,
        "field1": 26,
        "length(ms)": 196500,
        "liveness": 0.114,
        "popularity": 77,
        "release_date": "2020-02-29",
        "songname": "Bichiyal",
        "tempo": 93.956,
        "valence": 0.662
    },
    {
        "acousticness": 0.108,
        "album": "Diles",
        "artist": "Bad Bunny",
        "danceability": 0.813,
        "energy": 0.56,
        "field1": 27,
        "length(ms)": 286040,
        "liveness": 0.268,
        "popularity": 82,
        "release_date": "2016-08-26",
        "songname": "Diles",
        "tempo": 118.033,
        "valence": 0.287
    },
    {
        "acousticness": 0.0103,
        "album": "YHLQMDLG",
        "artist": "Bad Bunny",
        "danceability": 0.607,
        "energy": 0.829,
        "field1": 28,
        "length(ms)": 295176,
        "liveness": 0.107,
        "popularity": 79,
        "release_date": "2020-02-29",
        "songname": "Safaera",
        "tempo": 96.172,
        "valence": 0.685
    },
    {
        "acousticness": 0.0509,
        "album": "Un Verano Sin Ti",
        "artist": "Bad Bunny",
        "danceability": 0.629,
        "energy": 0.698,
        "field1": 29,
        "length(ms)": 201816,
        "liveness": 0.0909,
        "popularity": 81,
        "release_date": "2022-05-06",
        "songname": "El Apagón",
        "tempo": 117.765,
        "valence": 0.599
    },
    {
        "acousticness": 0.59,
        "album": "Un Verano Sin Ti",
        "artist": "Bad Bunny",
        "danceability": 0.777,
        "energy": 0.595,
        "field1": 30,
        "length(ms)": 244444,
        "liveness": 0.0669,
        "popularity": 84,
        "release_date": "2022-05-06",
        "songname": "Otro Atardecer",
        "tempo": 108.02,
        "valence": 0.546
    },
    {
        "acousticness": 0.021,
        "album": "YHLQMDLG",
        "artist": "Bad Bunny",
        "danceability": 0.86,
        "energy": 0.758,
        "field1": 31,
        "length(ms)": 172127,
        "liveness": 0.344,
        "popularity": 78,
        "release_date": "2020-02-29",
        "songname": "Yo Perreo Sola",
        "tempo": 97.014,
        "valence": 0.453
    },
    {
        "acousticness": 0.985,
        "album": "Amorfoda",
        "artist": "Bad Bunny",
        "danceability": 0.749,
        "energy": 0.418,
        "field1": 32,
        "length(ms)": 153887,
        "liveness": 0.0832,
        "popularity": 78,
        "release_date": "2018-02-15",
        "songname": "Amorfoda",
        "tempo": 147.887,
        "valence": 0.307
    },
    {
        "acousticness": 0.0303,
        "album": "EL ÚLTIMO TOUR DEL MUNDO",
        "artist": "Bad Bunny",
        "danceability": 0.856,
        "energy": 0.618,
        "field1": 33,
        "length(ms)": 203200,
        "liveness": 0.0866,
        "popularity": 81,
        "release_date": "2020-11-27",
        "songname": "LA NOCHE DE ANOCHE",
        "tempo": 81.993,
        "valence": 0.391
    },
    {
        "acousticness": 0.821,
        "album": "X 100PRE",
        "artist": "Bad Bunny",
        "danceability": 0.759,
        "energy": 0.536,
        "field1": 34,
        "length(ms)": 208079,
        "liveness": 0.107,
        "popularity": 74,
        "release_date": "2018-12-23",
        "songname": "Estamos Bien",
        "tempo": 119.883,
        "valence": 0.439
    },
    {
        "acousticness": 0.556,
        "album": "X 100PRE",
        "artist": "Bad Bunny",
        "danceability": 0.826,
        "energy": 0.449,
        "field1": 35,
        "length(ms)": 236215,
        "liveness": 0.273,
        "popularity": 75,
        "release_date": "2018-12-23",
        "songname": "NI BIEN NI MAL",
        "tempo": 128.028,
        "valence": 0.337
    },
    {
        "acousticness": 0.207,
        "album": "Un Verano Sin Ti",
        "artist": "Bad Bunny",
        "danceability": 0.839,
        "energy": 0.69,
        "field1": 36,
        "length(ms)": 196412,
        "liveness": 0.176,
        "popularity": 86,
        "release_date": "2022-05-06",
        "songname": "Un Coco",
        "tempo": 151.991,
        "valence": 0.744
    },
    {
        "acousticness": 0.683,
        "album": "Soy Peor",
        "artist": "Bad Bunny",
        "danceability": 0.808,
        "energy": 0.611,
        "field1": 37,
        "length(ms)": 257384,
        "liveness": 0.114,
        "popularity": 77,
        "release_date": "2016-12-08",
        "songname": "Soy Peor",
        "tempo": 116.011,
        "valence": 0.172
    },
    {
        "acousticness": 0.197,
        "album": "X 100PRE",
        "artist": "Bad Bunny",
        "danceability": 0.514,
        "energy": 0.646,
        "field1": 38,
        "length(ms)": 233128,
        "liveness": 0.0958,
        "popularity": 78,
        "release_date": "2018-12-23",
        "songname": "Otra Noche en Miami",
        "tempo": 88.661,
        "valence": 0.297
    },
    {
        "acousticness": 0.762,
        "album": "Un Verano Sin Ti",
        "artist": "Bad Bunny",
        "danceability": 0.797,
        "energy": 0.616,
        "field1": 39,
        "length(ms)": 339611,
        "liveness": 0.0979,
        "popularity": 84,
        "release_date": "2022-05-06",
        "songname": "Andrea",
        "tempo": 103.071,
        "valence": 0.451
    },
    {
        "acousticness": 0.423,
        "album": "Un Verano Sin Ti",
        "artist": "Bad Bunny",
        "danceability": 0.861,
        "energy": 0.645,
        "field1": 40,
        "length(ms)": 210989,
        "liveness": 0.349,
        "popularity": 83,
        "release_date": "2022-05-06",
        "songname": "Aguacero",
        "tempo": 121.391,
        "valence": 0.668
    },
    {
        "acousticness": 0.422,
        "album": "Volví",
        "artist": "Aventura",
        "danceability": 0.725,
        "energy": 0.86,
        "field1": 41,
        "length(ms)": 230125,
        "liveness": 0.0674,
        "popularity": 82,
        "release_date": "2021-08-03",
        "songname": "Volví",
        "tempo": 175.896,
        "valence": 0.791
    },
    {
        "acousticness": 0.267,
        "album": "Ignorantes",
        "artist": "Bad Bunny",
        "danceability": 0.85,
        "energy": 0.536,
        "field1": 42,
        "length(ms)": 210606,
        "liveness": 0.0996,
        "popularity": 71,
        "release_date": "2020-02-14",
        "songname": "Ignorantes",
        "tempo": 96.029,
        "valence": 0.505
    },
    {
        "acousticness": 0.0275,
        "album": "OASIS",
        "artist": "J Balvin",
        "danceability": 0.639,
        "energy": 0.791,
        "field1": 43,
        "length(ms)": 222346,
        "liveness": 0.362,
        "popularity": 80,
        "release_date": "2019-06-28",
        "songname": "QUE PRETENDES",
        "tempo": 92.603,
        "valence": 0.939
    },
    {
        "acousticness": 0.361,
        "album": "Soltera (Remix)",
        "artist": "Lunay",
        "danceability": 0.795,
        "energy": 0.783,
        "field1": 44,
        "length(ms)": 266086,
        "liveness": 0.437,
        "popularity": 73,
        "release_date": "2019-05-10",
        "songname": "Soltera - Remix",
        "tempo": 92.01,
        "valence": 0.799
    },
    {
        "acousticness": 0.132,
        "album": "YHLQMDLG",
        "artist": "Bad Bunny",
        "danceability": 0.55,
        "energy": 0.598,
        "field1": 45,
        "length(ms)": 232496,
        "liveness": 0.0955,
        "popularity": 80,
        "release_date": "2020-02-29",
        "songname": "Una Vez",
        "tempo": 83.836,
        "valence": 0.543
    },
    {
        "acousticness": 0.287,
        "album": "Solo de Mi",
        "artist": "Bad Bunny",
        "danceability": 0.743,
        "energy": 0.73,
        "field1": 46,
        "length(ms)": 197967,
        "liveness": 0.0778,
        "popularity": 68,
        "release_date": "2018-12-14",
        "songname": "Solo de Mi",
        "tempo": 179.972,
        "valence": 0.15
    },
    {
        "acousticness": 0.519,
        "album": "Si Tu Novio Te Deja Sola",
        "artist": "J Balvin",
        "danceability": 0.718,
        "energy": 0.46,
        "field1": 47,
        "length(ms)": 243560,
        "liveness": 0.0981,
        "popularity": 75,
        "release_date": "2017-03-03",
        "songname": "Si Tu Novio Te Deja Sola",
        "tempo": 121.927,
        "valence": 0.52
    },
    {
        "acousticness": 0.869,
        "album": "EL ÚLTIMO TOUR DEL MUNDO",
        "artist": "Bad Bunny",
        "danceability": 0.584,
        "energy": 0.411,
        "field1": 48,
        "length(ms)": 217768,
        "liveness": 0.0955,
        "popularity": 77,
        "release_date": "2020-11-27",
        "songname": "HACIENDO QUE ME AMAS",
        "tempo": 169.934,
        "valence": 0.412
    },
    {
        "acousticness": 0.0327,
        "album": "X 100PRE",
        "artist": "Bad Bunny",
        "danceability": 0.655,
        "energy": 0.725,
        "field1": 49,
        "length(ms)": 300579,
        "liveness": 0.0611,
        "popularity": 76,
        "release_date": "2018-12-23",
        "songname": "La Romana",
        "tempo": 125.8,
        "valence": 0.326
    },
    {
        "acousticness": 0.2,
        "album": "YHLQMDLG",
        "artist": "Bad Bunny",
        "danceability": 0.762,
        "energy": 0.801,
        "field1": 50,
        "length(ms)": 136892,
        "liveness": 0.254,
        "popularity": 78,
        "release_date": "2020-02-29",
        "songname": "La Zona",
        "tempo": 93.992,
        "valence": 0.81
    },
    {
        "acousticness": 0.228,
        "album": "Chambea",
        "artist": "Bad Bunny",
        "danceability": 0.856,
        "energy": 0.866,
        "field1": 51,
        "length(ms)": 192001,
        "liveness": 0.164,
        "popularity": 70,
        "release_date": "2017-12-01",
        "songname": "Chambea",
        "tempo": 116.005,
        "valence": 0.638
    },
    {
        "acousticness": 0.423,
        "album": "Sensualidad",
        "artist": "Various Artists",
        "danceability": 0.807,
        "energy": 0.681,
        "field1": 52,
        "length(ms)": 297485,
        "liveness": 0.0962,
        "popularity": 72,
        "release_date": "2017-11-03",
        "songname": "Sensualidad",
        "tempo": 140.006,
        "valence": 0.676
    },
    {
        "acousticness": 0.123,
        "album": "Un Verano Sin Ti",
        "artist": "Bad Bunny",
        "danceability": 0.817,
        "energy": 0.67,
        "field1": 53,
        "length(ms)": 208615,
        "liveness": 0.128,
        "popularity": 85,
        "release_date": "2022-05-06",
        "songname": "Dos Mil 16",
        "tempo": 130.058,
        "valence": 0.495
    },
    {
        "acousticness": 0.196,
        "album": "Vuelve",
        "artist": "Daddy Yankee",
        "danceability": 0.734,
        "energy": 0.531,
        "field1": 54,
        "length(ms)": 279613,
        "liveness": 0.119,
        "popularity": 78,
        "release_date": "2017-09-29",
        "songname": "Vuelve",
        "tempo": 130.024,
        "valence": 0.199
    },
    {
        "acousticness": 0.505,
        "album": "EL ÚLTIMO TOUR DEL MUNDO",
        "artist": "Bad Bunny",
        "danceability": 0.693,
        "energy": 0.549,
        "field1": 55,
        "length(ms)": 221186,
        "liveness": 0.324,
        "popularity": 73,
        "release_date": "2020-11-27",
        "songname": "ANTES QUE SE ACABE",
        "tempo": 139.988,
        "valence": 0.473
    },
    {
        "acousticness": 0.337,
        "album": "Loca Remix",
        "artist": "KHEA",
        "danceability": 0.795,
        "energy": 0.751,
        "field1": 56,
        "length(ms)": 346460,
        "liveness": 0.0983,
        "popularity": 72,
        "release_date": "2018-03-16",
        "songname": "Loca - Remix",
        "tempo": 113.033,
        "valence": 0.537
    },
    {
        "acousticness": 0.00536,
        "album": "UN DIA (ONE DAY) (Feat. Tainy)",
        "artist": "J Balvin",
        "danceability": 0.571,
        "energy": 0.693,
        "field1": 57,
        "length(ms)": 232253,
        "liveness": 0.173,
        "popularity": 74,
        "release_date": "2020-07-24",
        "songname": "UN DIA (ONE DAY) (Feat. Tainy)",
        "tempo": 168.169,
        "valence": 0.393
    },
    {
        "acousticness": 0.0475,
        "album": "YHLQMDLG",
        "artist": "Bad Bunny",
        "danceability": 0.882,
        "energy": 0.612,
        "field1": 58,
        "length(ms)": 160638,
        "liveness": 0.182,
        "popularity": 72,
        "release_date": "2020-02-29",
        "songname": "Pero Ya No",
        "tempo": 147.982,
        "valence": 0.742
    },
    {
        "acousticness": 0.486,
        "album": "Dime Si Te Acuerdas",
        "artist": "Bad Bunny",
        "danceability": 0.74,
        "energy": 0.595,
        "field1": 59,
        "length(ms)": 187272,
        "liveness": 0.163,
        "popularity": 71,
        "release_date": "2018-02-22",
        "songname": "Dime Si Te Acuerdas",
        "tempo": 131.96,
        "valence": 0.316
    },
    {
        "acousticness": 0.132,
        "album": "Madura",
        "artist": "Cosculluela",
        "danceability": 0.794,
        "energy": 0.546,
        "field1": 60,
        "length(ms)": 190995,
        "liveness": 0.139,
        "popularity": 72,
        "release_date": "2018-04-13",
        "songname": "Madura",
        "tempo": 175.96,
        "valence": 0.759
    },
    {
        "acousticness": 0.464,
        "album": "Emmanuel",
        "artist": "Anuel AA",
        "danceability": 0.691,
        "energy": 0.765,
        "field1": 61,
        "length(ms)": 246000,
        "liveness": 0.203,
        "popularity": 75,
        "release_date": "2020-05-29",
        "songname": "Hasta Que Dios Diga",
        "tempo": 174.021,
        "valence": 0.855
    },
    {
        "acousticness": 0.099,
        "album": "Invasion of Privacy",
        "artist": "Cardi B",
        "danceability": 0.816,
        "energy": 0.726,
        "field1": 62,
        "length(ms)": 253390,
        "liveness": 0.372,
        "popularity": 78,
        "release_date": "2018-04-06",
        "songname": "I Like It",
        "tempo": 136.048,
        "valence": 0.65
    },
    {
        "acousticness": 0.689,
        "album": "Tu No Metes Cabra",
        "artist": "Bad Bunny",
        "danceability": 0.86,
        "energy": 0.641,
        "field1": 63,
        "length(ms)": 170762,
        "liveness": 0.107,
        "popularity": 72,
        "release_date": "2017-07-06",
        "songname": "Tu No Metes Cabra",
        "tempo": 92.013,
        "valence": 0.432
    },
    {
        "acousticness": 0.0832,
        "album": "YHLQMDLG",
        "artist": "Bad Bunny",
        "danceability": 0.802,
        "energy": 0.787,
        "field1": 64,
        "length(ms)": 167975,
        "liveness": 0.153,
        "popularity": 74,
        "release_date": "2020-02-29",
        "songname": "Que Malo",
        "tempo": 94.026,
        "valence": 0.446
    },
    {
        "acousticness": 0.125,
        "album": "OASIS",
        "artist": "J Balvin",
        "danceability": 0.627,
        "energy": 0.675,
        "field1": 65,
        "length(ms)": 277106,
        "liveness": 0.0784,
        "popularity": 82,
        "release_date": "2019-06-28",
        "songname": "UN PESO",
        "tempo": 79.31,
        "valence": 0.961
    },
    {
        "acousticness": 0.447,
        "album": "LAS QUE NO IBAN A SALIR",
        "artist": "Bad Bunny",
        "danceability": 0.75,
        "energy": 0.741,
        "field1": 66,
        "length(ms)": 209180,
        "liveness": 0.121,
        "popularity": 75,
        "release_date": "2020-05-10",
        "songname": "CANCIÓN CON YANDEL",
        "tempo": 79.968,
        "valence": 0.495
    },
    {
        "acousticness": 0.412,
        "album": "LAS QUE NO IBAN A SALIR",
        "artist": "Bad Bunny",
        "danceability": 0.712,
        "energy": 0.599,
        "field1": 67,
        "length(ms)": 178000,
        "liveness": 0.103,
        "popularity": 70,
        "release_date": "2020-05-10",
        "songname": "BYE ME FUI",
        "tempo": 179.788,
        "valence": 0.588
    },
    {
        "acousticness": 0.016,
        "album": "LAS QUE NO IBAN A SALIR",
        "artist": "Bad Bunny",
        "danceability": 0.772,
        "energy": 0.83,
        "field1": 68,
        "length(ms)": 194200,
        "liveness": 0.0843,
        "popularity": 69,
        "release_date": "2020-05-10",
        "songname": "PA' ROMPERLA",
        "tempo": 94.011,
        "valence": 0.697
    },
    {
        "acousticness": 0.348,
        "album": "Pa Ti",
        "artist": "Bad Bunny",
        "danceability": 0.76,
        "energy": 0.718,
        "field1": 69,
        "length(ms)": 191294,
        "liveness": 0.0982,
        "popularity": 75,
        "release_date": "2017-01-02",
        "songname": "Pa Ti",
        "tempo": 128.14,
        "valence": 0.557
    },
    {
        "acousticness": 0.627,
        "album": "X 100PRE",
        "artist": "Bad Bunny",
        "danceability": 0.651,
        "energy": 0.575,
        "field1": 70,
        "length(ms)": 229455,
        "liveness": 0.0961,
        "popularity": 69,
        "release_date": "2018-12-23",
        "songname": "Caro",
        "tempo": 160.007,
        "valence": 0.248
    },
    {
        "acousticness": 0.0385,
        "album": "Gangalee",
        "artist": "Farruko",
        "danceability": 0.771,
        "energy": 0.796,
        "field1": 71,
        "length(ms)": 289906,
        "liveness": 0.218,
        "popularity": 65,
        "release_date": "2019-04-26",
        "songname": "La Cartera",
        "tempo": 87.985,
        "valence": 0.636
    },
    {
        "acousticness": 0.092,
        "album": "YHLQMDLG",
        "artist": "Bad Bunny",
        "danceability": 0.761,
        "energy": 0.732,
        "field1": 72,
        "length(ms)": 243275,
        "liveness": 0.0716,
        "popularity": 71,
        "release_date": "2020-02-29",
        "songname": "25/8",
        "tempo": 151.982,
        "valence": 0.542
    },
    {
        "acousticness": 0.0583,
        "album": "#Update",
        "artist": "Yandel",
        "danceability": 0.808,
        "energy": 0.69,
        "field1": 73,
        "length(ms)": 223146,
        "liveness": 0.103,
        "popularity": 67,
        "release_date": "2017-09-08",
        "songname": "Explícale (feat. Bad Bunny)",
        "tempo": 125.086,
        "valence": 0.64
    },
    {
        "acousticness": 0.54,
        "album": "Tu No Vive Asi (feat. Mambo Kingz & DJ Luian)",
        "artist": "Arcangel",
        "danceability": 0.815,
        "energy": 0.514,
        "field1": 74,
        "length(ms)": 264000,
        "liveness": 0.611,
        "popularity": 79,
        "release_date": "2016-09-30",
        "songname": "Tu No Vive Asi (feat. Mambo Kingz & DJ Luian)",
        "tempo": 120.054,
        "valence": 0.623
    },
    {
        "acousticness": 0.479,
        "album": "LOYAL (feat. Drake and Bad Bunny) [Remix]",
        "artist": "PARTYNEXTDOOR",
        "danceability": 0.877,
        "energy": 0.529,
        "field1": 75,
        "length(ms)": 281119,
        "liveness": 0.094,
        "popularity": 53,
        "release_date": "2020-02-07",
        "songname": "LOYAL (feat. Drake and Bad Bunny) - Remix",
        "tempo": 104.984,
        "valence": 0.422
    },
    {
        "acousticness": 0.551,
        "album": "Me Mata",
        "artist": "Bad Bunny",
        "danceability": 0.841,
        "energy": 0.53,
        "field1": 76,
        "length(ms)": 412631,
        "liveness": 0.119,
        "popularity": 74,
        "release_date": "2017-04-11",
        "songname": "Me Mata",
        "tempo": 114.028,
        "valence": 0.686
    },
    {
        "acousticness": 0.0651,
        "album": "Bellacoso",
        "artist": "Residente",
        "danceability": 0.774,
        "energy": 0.851,
        "field1": 77,
        "length(ms)": 257864,
        "liveness": 0.0568,
        "popularity": 68,
        "release_date": "2019-07-26",
        "songname": "Bellacoso",
        "tempo": 180.086,
        "valence": 0.695
    },
    {
        "acousticness": 0.0464,
        "album": "Victory",
        "artist": "Wisin",
        "danceability": 0.797,
        "energy": 0.804,
        "field1": 78,
        "length(ms)": 386333,
        "liveness": 0.317,
        "popularity": 68,
        "release_date": "2017-12-01",
        "songname": "Escápate Conmigo (feat. Ozuna, Bad Bunny, De La Ghetto, Arcángel, Noriel & Almighty) - Remix",
        "tempo": 91.973,
        "valence": 0.451
    },
    {
        "acousticness": 0.448,
        "album": "Carbon Fiber Hits",
        "artist": "Carbon Fiber Music",
        "danceability": 0.685,
        "energy": 0.725,
        "field1": 79,
        "length(ms)": 331413,
        "liveness": 0.194,
        "popularity": 67,
        "release_date": "2018-12-21",
        "songname": "Diabla (Official Remix)",
        "tempo": 137.946,
        "valence": 0.575
    },
    {
        "acousticness": 0.641,
        "album": "Me Acostumbre (feat. Bad Bunny)",
        "artist": "Arcangel",
        "danceability": 0.808,
        "energy": 0.586,
        "field1": 80,
        "length(ms)": 263288,
        "liveness": 0.14,
        "popularity": 71,
        "release_date": "2017-04-11",
        "songname": "Me Acostumbre (feat. Bad Bunny)",
        "tempo": 124.041,
        "valence": 0.568
    },
    {
        "acousticness": 0.602,
        "album": "YHLQMDLG",
        "artist": "Bad Bunny",
        "danceability": 0.631,
        "energy": 0.665,
        "field1": 81,
        "length(ms)": 157967,
        "liveness": 0.152,
        "popularity": 70,
        "release_date": "2020-02-29",
        "songname": "<3",
        "tempo": 80.353,
        "valence": 0.634
    },
    {
        "acousticness": 0.415,
        "album": "¿Cual Es Tu Plan?",
        "artist": "Bad Bunny",
        "danceability": 0.822,
        "energy": 0.601,
        "field1": 82,
        "length(ms)": 243700,
        "liveness": 0.0797,
        "popularity": 70,
        "release_date": "2018-08-17",
        "songname": "¿Cual Es Tu Plan?",
        "tempo": 96.123,
        "valence": 0.872
    },
    {
        "acousticness": 0.0353,
        "album": "No Te Hagas",
        "artist": "Jory Boy",
        "danceability": 0.748,
        "energy": 0.69,
        "field1": 83,
        "length(ms)": 233250,
        "liveness": 0.315,
        "popularity": 75,
        "release_date": "2017-03-11",
        "songname": "No Te Hagas",
        "tempo": 131.972,
        "valence": 0.433
    },
    {
        "acousticness": 0.0139,
        "album": "X 100PRE",
        "artist": "Bad Bunny",
        "danceability": 0.85,
        "energy": 0.5,
        "field1": 84,
        "length(ms)": 170509,
        "liveness": 0.0947,
        "popularity": 69,
        "release_date": "2018-12-23",
        "songname": "200 Mph",
        "tempo": 160.02,
        "valence": 0.816
    },
    {
        "acousticness": 0.0947,
        "album": "EL ÚLTIMO TOUR DEL MUNDO",
        "artist": "Bad Bunny",
        "danceability": 0.688,
        "energy": 0.881,
        "field1": 85,
        "length(ms)": 191526,
        "liveness": 0.0804,
        "popularity": 69,
        "release_date": "2020-11-27",
        "songname": "YO VISTO ASÍ",
        "tempo": 123.013,
        "valence": 0.677
    },
    {
        "acousticness": 0.117,
        "album": "YHLQMDLG",
        "artist": "Bad Bunny",
        "danceability": 0.71,
        "energy": 0.81,
        "field1": 86,
        "length(ms)": 159282,
        "liveness": 0.154,
        "popularity": 74,
        "release_date": "2020-02-29",
        "songname": "Soliá",
        "tempo": 92.041,
        "valence": 0.184
    },
    {
        "acousticness": 0.668,
        "album": "X 100PRE",
        "artist": "Bad Bunny",
        "danceability": 0.767,
        "energy": 0.379,
        "field1": 87,
        "length(ms)": 230577,
        "liveness": 0.217,
        "popularity": 70,
        "release_date": "2018-12-23",
        "songname": "Como Antes",
        "tempo": 103.956,
        "valence": 0.252
    },
    {
        "acousticness": 0.0378,
        "album": "LAS QUE NO IBAN A SALIR",
        "artist": "Bad Bunny",
        "danceability": 0.828,
        "energy": 0.581,
        "field1": 88,
        "length(ms)": 155060,
        "liveness": 0.103,
        "popularity": 66,
        "release_date": "2020-05-10",
        "songname": "BENDICIONES",
        "tempo": 143.995,
        "valence": 0.843
    },
    {
        "acousticness": 0.41,
        "album": "Sexto Sentido (feat. Bad Bunny)",
        "artist": "Gigolo Y La Exce",
        "danceability": 0.715,
        "energy": 0.615,
        "field1": 89,
        "length(ms)": 227291,
        "liveness": 0.126,
        "popularity": 70,
        "release_date": "2017-08-17",
        "songname": "Sexto Sentido (feat. Bad Bunny)",
        "tempo": 140.977,
        "valence": 0.52
    },
    {
        "acousticness": 0.0732,
        "album": "OASIS",
        "artist": "J Balvin",
        "danceability": 0.825,
        "energy": 0.807,
        "field1": 90,
        "length(ms)": 218826,
        "liveness": 0.138,
        "popularity": 72,
        "release_date": "2019-06-28",
        "songname": "COMO UN BEBÉ",
        "tempo": 103.053,
        "valence": 0.816
    },
    {
        "acousticness": 0.137,
        "album": "X 100PRE",
        "artist": "Bad Bunny",
        "danceability": 0.787,
        "energy": 0.705,
        "field1": 91,
        "length(ms)": 188654,
        "liveness": 0.108,
        "popularity": 66,
        "release_date": "2018-12-23",
        "songname": "Cuando Perriabas",
        "tempo": 81.998,
        "valence": 0.499
    },
    {
        "acousticness": 0.0445,
        "album": "Ahora Me Llama (Remix)",
        "artist": "KAROL G",
        "danceability": 0.671,
        "energy": 0.631,
        "field1": 92,
        "length(ms)": 251906,
        "liveness": 0.101,
        "popularity": 61,
        "release_date": "2017-10-06",
        "songname": "Ahora Me Llama - Remix",
        "tempo": 134.986,
        "valence": 0.205
    },
    {
        "acousticness": 0.176,
        "album": "Los Campeones del Pueblo \"The Big Leagues\"",
        "artist": "Wisin & Yandel",
        "danceability": 0.829,
        "energy": 0.723,
        "field1": 93,
        "length(ms)": 237906,
        "liveness": 0.0877,
        "popularity": 65,
        "release_date": "2018-12-14",
        "songname": "Dame Algo",
        "tempo": 92.956,
        "valence": 0.721
    },
    {
        "acousticness": 0.408,
        "album": "La Oscuridad",
        "artist": "Bryant Myers",
        "danceability": 0.692,
        "energy": 0.719,
        "field1": 94,
        "length(ms)": 264905,
        "liveness": 0.0986,
        "popularity": 73,
        "release_date": "2018-07-27",
        "songname": "Triste",
        "tempo": 130.053,
        "valence": 0.266
    },
    {
        "acousticness": 0.0732,
        "album": "YHLQMDLG",
        "artist": "Bad Bunny",
        "danceability": 0.81,
        "energy": 0.854,
        "field1": 95,
        "length(ms)": 227939,
        "liveness": 0.123,
        "popularity": 71,
        "release_date": "2020-02-29",
        "songname": "Está Cabrón Ser Yo",
        "tempo": 154.083,
        "valence": 0.879
    },
    {
        "acousticness": 0.321,
        "album": "LAS QUE NO IBAN A SALIR",
        "artist": "Bad Bunny",
        "danceability": 0.59,
        "energy": 0.729,
        "field1": 96,
        "length(ms)": 202240,
        "liveness": 0.659,
        "popularity": 67,
        "release_date": "2020-05-10",
        "songname": "BAD CON NICKY",
        "tempo": 93.094,
        "valence": 0.712
    },
    {
        "acousticness": 0.588,
        "album": "Soy El Diablo (Remix)",
        "artist": "Natanael Cano",
        "danceability": 0.681,
        "energy": 0.686,
        "field1": 97,
        "length(ms)": 193621,
        "liveness": 0.114,
        "popularity": 66,
        "release_date": "2019-10-25",
        "songname": "Soy El Diablo - Remix",
        "tempo": 109.191,
        "valence": 0.961
    },
    {
        "acousticness": 0.0869,
        "album": "YHLQMDLG",
        "artist": "Bad Bunny",
        "danceability": 0.683,
        "energy": 0.677,
        "field1": 98,
        "length(ms)": 240253,
        "liveness": 0.0998,
        "popularity": 71,
        "release_date": "2020-02-29",
        "songname": "Hablamos Mañana",
        "tempo": 156.019,
        "valence": 0.514
    },
    {
        "acousticness": 0.0171,
        "album": "OASIS",
        "artist": "J Balvin",
        "danceability": 0.45,
        "energy": 0.842,
        "field1": 99,
        "length(ms)": 187333,
        "liveness": 0.377,
        "popularity": 68,
        "release_date": "2019-06-28",
        "songname": "MOJAITA",
        "tempo": 172.069,
        "valence": 0.885
    }
]